aiohttp_json_api/__init__.py
aiohttp_json_api/common.py
aiohttp_json_api/context.py
aiohttp_json_api/controller.py
aiohttp_json_api/encoder.py
aiohttp_json_api/errors.py
aiohttp_json_api/handlers.py
aiohttp_json_api/helpers.py
aiohttp_json_api/jsonpointer.py
aiohttp_json_api/middleware.py
aiohttp_json_api/pagination.py
aiohttp_json_api/registry.py
aiohttp_json_api/schema.py
aiohttp_json_api/typings.py
aiohttp_json_api/utils.py
aiohttp_json_api/abc/__init__.py
aiohttp_json_api/abc/contoller.py
aiohttp_json_api/abc/field.py
aiohttp_json_api/abc/processors.py
aiohttp_json_api/abc/schema.py
aiohttp_json_api/fields/__init__.py
aiohttp_json_api/fields/attributes.py
aiohttp_json_api/fields/base.py
aiohttp_json_api/fields/decorators.py
aiohttp_json_api/fields/relationships.py
aiohttp_json_api/fields/trafarets.py
aiohttp_json_api-0.37.0.dist-info/DESCRIPTION.rst
aiohttp_json_api-0.37.0.dist-info/METADATA
aiohttp_json_api-0.37.0.dist-info/RECORD
aiohttp_json_api-0.37.0.dist-info/WHEEL
aiohttp_json_api-0.37.0.dist-info/metadata.json
aiohttp_json_api-0.37.0.dist-info/top_level.txt
