Metadata-Version: 2.0
Name: aiohttp-json-api
Version: 0.37.0
Summary: JSON API driven by aiohttp
Home-page: https://github.com/vovanbo/aiohttp_json_api
Author: Vladimir Bolshakov
Author-email: vovanbo@gmail.com
License: MIT license
Keywords: aiohttp_json_api
Platform: UNKNOWN
Classifier: Development Status :: 3 - Alpha
Classifier: Intended Audience :: Developers
Classifier: Framework :: AsyncIO
Classifier: License :: OSI Approved :: MIT License
Classifier: Natural Language :: English
Classifier: Programming Language :: Python :: 3
Classifier: Programming Language :: Python :: 3.6
Classifier: Topic :: Internet :: WWW/HTTP
Requires-Dist: aiohttp (>=2.0.0)
Requires-Dist: inflection (>=0.3.1)
Requires-Dist: multidict (>=3.3.0)
Requires-Dist: jsonpointer (>=1.10)
Requires-Dist: python-dateutil (>=2.6.0)
Requires-Dist: python-mimeparse (>=1.6.0)
Requires-Dist: trafaret (>=1.0.2)
Requires-Dist: yarl (>=0.13.0)
